README.md
setup.cfg
setup.py
typed_print/__init__.py
typed_print/typed_print.py
typed_print.egg-info/PKG-INFO
typed_print.egg-info/SOURCES.txt
typed_print.egg-info/dependency_links.txt
typed_print.egg-info/requires.txt
typed_print.egg-info/top_level.txt