Metadata-Version: 1.1
Name: typed-print
Version: 0.1
Summary: Printing function with automated coloring.
Home-page: https://github.com/DmitryUlyanov/typed_print
Author: Dmitry Ulyanov
Author-email: dmitry.ulyanov.msu@gmail.com
License: MIT
Download-URL: https://github.com/DmitryUlyanov/typed_print/archive/0.1.tar.gz
Platform: UNKNOWN
